TracWatchlistPlugin-3.0.0.dist-info/METADATA
TracWatchlistPlugin-3.0.0.dist-info/RECORD
TracWatchlistPlugin-3.0.0.dist-info/WHEEL
TracWatchlistPlugin-3.0.0.dist-info/entry_points.txt
TracWatchlistPlugin-3.0.0.dist-info/top_level.txt
tracwatchlist/__init__.py
tracwatchlist/api.py
tracwatchlist/db.py
tracwatchlist/manual.py
tracwatchlist/nav.py
tracwatchlist/plugin.py
tracwatchlist/ticket.py
tracwatchlist/translation.py
tracwatchlist/util.py
tracwatchlist/wiki.py
tracwatchlist/htdocs/css/anytime.css
tracwatchlist/htdocs/css/dataTable.css
tracwatchlist/htdocs/css/jquery.autocomplete.css
tracwatchlist/htdocs/css/tablesorter.css
tracwatchlist/htdocs/css/watchlist.css
tracwatchlist/htdocs/ico/asc.gif
tracwatchlist/htdocs/ico/bg.gif
tracwatchlist/htdocs/ico/desc.gif
tracwatchlist/htdocs/ico/diff.png
tracwatchlist/htdocs/ico/first.png
tracwatchlist/htdocs/ico/history.png
tracwatchlist/htdocs/ico/last.png
tracwatchlist/htdocs/ico/next.png
tracwatchlist/htdocs/ico/prev.png
tracwatchlist/htdocs/ico/unwatch.png
tracwatchlist/htdocs/js/anytime.js
tracwatchlist/htdocs/js/autocomplete.js
tracwatchlist/htdocs/js/dynamictables.js
tracwatchlist/htdocs/js/jookie.js
tracwatchlist/htdocs/js/jquery.autocomplete.js
tracwatchlist/htdocs/js/jquery.dataTables.min.js
tracwatchlist/htdocs/js/orderadd.js
tracwatchlist/htdocs/js/watchlist.js
tracwatchlist/locale/de/LC_MESSAGES/watchlist.mo
tracwatchlist/manuals/de.txt
tracwatchlist/manuals/en-GB.txt
tracwatchlist/manuals/en-US.txt
tracwatchlist/manuals/attachments/de/screenshot.png
tracwatchlist/render/__init__.py
tracwatchlist/templates/orderadd.html
tracwatchlist/templates/watchlist.html
tracwatchlist/templates/watchlist_manual.html
tracwatchlist/templates/watchlist_prefs.html
tracwatchlist/templates/watchlist_prefs_main.html
tracwatchlist/templates/wl-ticket.html
tracwatchlist/templates/wl-wiki.html
